[{"title":"A Book of Hymns for Public and Private Devotion (15th ed.)","hymnalID":"BHPPD866","number":"365","text":"Now that the sun is beaming bright,\n\nImplore we, bending low,\n\nThat He, the uncreated Light,\n\nMay guide us as we go.\n\nNo sinful word, nor deed of wrong,\n\nNor thoughts that idly rove,\n\nBut simple truth be on our tongue,\n\nAnd in our hearts be love.\n\nAnd while the hours in order flow,\n\nSecurely keep, O God,\n\nOur hearts, beleaguered by the foe\n\nThat tempts our every road.\n\nAnd grant that to Thine honor, Lord,\n\nOur daily toil may tend;\n\nThat we begin it at Thy word,\n\nAnd in Thy favor end.\n\n","doNotDisplay":"0","date":"1866","classifications":"Gender Neutral"}]